setup.py
botoweb/__init__.py
botoweb/config.py
botoweb/encoder.py
botoweb/environment.py
botoweb/exceptions.py
botoweb/fixed_datetime.py
botoweb/request.py
botoweb/response.py
botoweb/status.py
botoweb/testbase.py
botoweb/xmlize.py
botoweb/xslt_functions.py
botoweb.egg-info/PKG-INFO
botoweb.egg-info/SOURCES.txt
botoweb.egg-info/dependency_links.txt
botoweb.egg-info/requires.txt
botoweb.egg-info/top_level.txt
botoweb/appserver/__init__.py
botoweb/appserver/auth_layer.py
botoweb/appserver/cache_layer.py
botoweb/appserver/filter_mapper.py
botoweb/appserver/filter_resolver.py
botoweb/appserver/socket.py
botoweb/appserver/url_mapper.py
botoweb/appserver/wsgi_layer.py
botoweb/appserver/handlers/__init__.py
botoweb/appserver/handlers/db.py
botoweb/appserver/handlers/index.py
botoweb/appserver/handlers/login.py
botoweb/appserver/handlers/proxy.py
botoweb/appserver/handlers/robots.py
botoweb/appserver/handlers/trash.py
botoweb/appserver/handlers/user.py
botoweb/client/__init__.py
botoweb/client/connection.py
botoweb/client/environment.py
botoweb/client/query.py
botoweb/client/sax_handler.py
botoweb/db/__init__.py
botoweb/db/blob.py
botoweb/db/botomodel.py
botoweb/db/converter.py
botoweb/db/coremodel.py
botoweb/db/dynamo.py
botoweb/db/index.py
botoweb/db/key.py
botoweb/db/model.py
botoweb/db/property.py
botoweb/db/query.py
botoweb/db/sequence.py
botoweb/db/manager/__init__.py
botoweb/db/manager/dynamodbmanager.py
botoweb/db/manager/pgmanager.py
botoweb/db/manager/sdbmanager.py
botoweb/db/manager/xmlmanager.py
botoweb/filters/__init__.py
botoweb/resources/__init__.py
botoweb/resources/authorization.py
botoweb/resources/filter_rule.py
botoweb/resources/user.py
example/resources/__init__.py
example/resources/post.py
tools/botoweb
tools/botoweb_client
tools/bw_client_upload