Metadata-Version: 1.1
Name: botoweb
Version: 1.5.5
Summary: Boto based webapp framework
Home-page: http://botoweb.com
Author: Chris Moyer
Author-email: kopertop@gmail.com
License: MIT
Platform: Posix; MacOS X; Windows
Classifier: Development Status :: 3 - Alpha
Classifier: Intended Audience :: Developers
Classifier: License :: OSI Approved :: MIT License
Classifier: Operating System :: OS Independent
Classifier: Topic :: Internet
